classroom_pilot/__init__.py
classroom_pilot/__main__.py
classroom_pilot/_version.py
classroom_pilot/assignments/__init__.py
classroom_pilot/assignments/cycle_collaborator.py
classroom_pilot/assignments/manage.py
classroom_pilot/assignments/orchestrator.py
classroom_pilot/assignments/push_manager.py
classroom_pilot/assignments/setup.py
classroom_pilot/assignments/student_helper.py
classroom_pilot/automation/__init__.py
classroom_pilot/automation/cron_manager.py
classroom_pilot/automation/cron_sync.py
classroom_pilot/automation/scheduler.py
classroom_pilot/bash_wrapper.py
classroom_pilot/cli.py
classroom_pilot/cli_legacy.py
classroom_pilot/config/__init__.py
classroom_pilot/config/generator.py
classroom_pilot/config/global_config.py
classroom_pilot/config/loader.py
classroom_pilot/config/validator.py
classroom_pilot/config.py
classroom_pilot/repos/__init__.py
classroom_pilot/repos/collaborator.py
classroom_pilot/repos/fetch.py
classroom_pilot/scripts_legacy/add-secrets-to-students.sh
classroom_pilot/scripts_legacy/assignment-orchestrator.sh
classroom_pilot/scripts_legacy/cron-sync.sh
classroom_pilot/scripts_legacy/cycle-collaborator.sh
classroom_pilot/scripts_legacy/fetch-student-repos.sh
classroom_pilot/scripts_legacy/manage-cron.sh
classroom_pilot/scripts_legacy/push-to-classroom.sh
classroom_pilot/scripts_legacy/setup-assignment.sh
classroom_pilot/scripts_legacy/student-update-helper.sh
classroom_pilot/scripts_legacy/update-assignment.sh
classroom_pilot/secrets/__init__.py
classroom_pilot/secrets/github_secrets.py
classroom_pilot/secrets/manager.py
classroom_pilot/services/assignment_service.py
classroom_pilot/services/automation_service.py
classroom_pilot/services/repos_service.py
classroom_pilot/services/secrets_service.py
classroom_pilot/utils/__init__.py
classroom_pilot/utils/config.sh
classroom_pilot/utils/file_operations.py
classroom_pilot/utils/git.py
classroom_pilot/utils/github_api_client.py
classroom_pilot/utils/github_classroom_api.py
classroom_pilot-3.1.1b2.dist-info/METADATA
classroom_pilot-3.1.1b2.dist-info/WHEEL
classroom_pilot-3.1.1b2.dist-info/entry_points.txt
classroom_pilot-3.1.1b2.dist-info/licenses/LICENSE
classroom_pilot-3.1.1b2.dist-info/RECORD
