Metadata-Version: 2.4
Name: classroom-pilot
Version: 3.1.1b2
Summary: Modern Python CLI for automating GitHub Classroom assignment management
License: MIT
License-File: LICENSE
Keywords: github,classroom,education,automation,cli
Author: Hugo Valle
Author-email: hugovalle1@weber.edu
Requires-Python: >=3.10
Classifier: Development Status :: 4 - Beta
Classifier: Intended Audience :: Education
Classifier: Intended Audience :: Developers
Classifier: License :: OSI Approved :: MIT License
Classifier: Operating System :: OS Independent
Classifier: Programming Language :: Python :: 3
Classifier: Programming Language :: Python :: 3.10
Classifier: Programming Language :: Python :: 3.11
Classifier: Programming Language :: Python :: 3.12
Classifier: Topic :: Education
Classifier: Topic :: Software Development :: Version Control :: Git
Classifier: Topic :: System :: Systems Administration
Classifier: Environment :: Console
Provides-Extra: dev
Requires-Dist: PyGithub (>=1.59.0)
Requires-Dist: PyNaCl (>=1.5.0)
Requires-Dist: black (>=23.7.0) ; extra == "dev"
Requires-Dist: click (>=8.0.0,<8.2.0)
Requires-Dist: cryptography (>=41.0.0)
Requires-Dist: flake8 (>=6.0.0) ; extra == "dev"
Requires-Dist: isort (>=5.12.0) ; extra == "dev"
Requires-Dist: mypy (>=1.5.0) ; extra == "dev"
Requires-Dist: pre-commit (>=3.3.0) ; extra == "dev"
Requires-Dist: pytest (>=7.4.0) ; extra == "dev"
Requires-Dist: pytest-cov (>=4.1.0) ; extra == "dev"
Requires-Dist: pytest-mock (>=3.11.0) ; extra == "dev"
Requires-Dist: pyyaml (>=6.0.1)
Requires-Dist: requests (>=2.31.0)
Requires-Dist: typer (>=0.12.0)
Requires-Dist: types-PyYAML (>=6.0.12) ; extra == "dev"
Requires-Dist: types-requests (>=2.31.0) ; extra == "dev"
Project-URL: Bug Reports, https://github.com/hugo-valle/classroom-pilot/issues
Project-URL: Documentation, https://github.com/hugo-valle/classroom-pilot#readme
Project-URL: Feature Requests, https://github.com/hugo-valle/classroom-pilot/issues
Project-URL: Homepage, https://github.com/hugo-valle/classroom-pilot
Project-URL: Repository, https://github.com/hugo-valle/classroom-pilot
